huaweicloudsdkdataartsfabric/__init__.py
huaweicloudsdkdataartsfabric/v1/__init__.py
huaweicloudsdkdataartsfabric/v1/dataartsfabric_async_client.py
huaweicloudsdkdataartsfabric/v1/dataartsfabric_client.py
huaweicloudsdkdataartsfabric/v1/model/__init__.py
huaweicloudsdkdataartsfabric/v1/model/agency_policy.py
huaweicloudsdkdataartsfabric/v1/model/agency_type_body.py
huaweicloudsdkdataartsfabric/v1/model/agreement_rule.py
huaweicloudsdkdataartsfabric/v1/model/base_model.py
huaweicloudsdkdataartsfabric/v1/model/base_model_type.py
huaweicloudsdkdataartsfabric/v1/model/batch_create_fabric_workspace_tags_request.py
huaweicloudsdkdataartsfabric/v1/model/batch_create_fabric_workspace_tags_response.py
huaweicloudsdkdataartsfabric/v1/model/batch_create_tags_request_body.py
huaweicloudsdkdataartsfabric/v1/model/batch_delete_fabric_workspace_tags_request.py
huaweicloudsdkdataartsfabric/v1/model/batch_delete_fabric_workspace_tags_response.py
huaweicloudsdkdataartsfabric/v1/model/batch_delete_tags_request_body.py
huaweicloudsdkdataartsfabric/v1/model/cap_id.py
huaweicloudsdkdataartsfabric/v1/model/cap_ref.py
huaweicloudsdkdataartsfabric/v1/model/cap_version_id.py
huaweicloudsdkdataartsfabric/v1/model/cleanup_model_request.py
huaweicloudsdkdataartsfabric/v1/model/cleanup_model_response.py
huaweicloudsdkdataartsfabric/v1/model/count_tag_fabric_workspaces_request.py
huaweicloudsdkdataartsfabric/v1/model/count_tag_fabric_workspaces_response.py
huaweicloudsdkdataartsfabric/v1/model/create_agency_request.py
huaweicloudsdkdataartsfabric/v1/model/create_agency_response.py
huaweicloudsdkdataartsfabric/v1/model/create_agreement_request.py
huaweicloudsdkdataartsfabric/v1/model/create_agreement_response.py
huaweicloudsdkdataartsfabric/v1/model/create_endpoint_request.py
huaweicloudsdkdataartsfabric/v1/model/create_endpoint_response.py
huaweicloudsdkdataartsfabric/v1/model/create_message_notification_policy.py
huaweicloudsdkdataartsfabric-3.1.184.dist-info/METADATA
huaweicloudsdkdataartsfabric-3.1.184.dist-info/WHEEL
huaweicloudsdkdataartsfabric-3.1.184.dist-info/licenses/LICENSE
huaweicloudsdkdataartsfabric-3.1.184.dist-info/RECORD
